pipeline/CacheCommon/__init__.py
pipeline/CacheCommon/cacheCommonConnector.py
pipeline/CommonFunctions/StartupCommon.py
pipeline/CommonFunctions/__init__.py
pipeline/CommonFunctions/urn.py
pipeline/DBCommon/__init__.py
pipeline/DBCommon/dBCommonConnector.py
pipeline/DBCommon/models/__init__.py
pipeline/DBCommon/models/base.py
pipeline/QueueModels/__init__.py
pipeline/QueueModels/serviceRequest.py
pipeline/QueueModels/serviceResponse.py
pipeline/__init__.py
pipeline/exceptions.py
ipl_pipeline_py_common-0.10.2.dist-info/METADATA
ipl_pipeline_py_common-0.10.2.dist-info/WHEEL
ipl_pipeline_py_common-0.10.2.dist-info/RECORD
