Metadata-Version: 2.1
Name: ipl-pipeline-py-common
Version: 0.10.2
Summary: Common functions and modules for Python based IPL Pipeline Services
License: All Rights Reserved
Author: Vincent Lee
Author-email: vlee@vlee.me.uk
Requires-Python: >=3.11,<4.0
Classifier: License :: Other/Proprietary License
Classifier: Programming Language :: Python :: 3
Classifier: Programming Language :: Python :: 3.11
Classifier: Programming Language :: Python :: 3.12
Requires-Dist: asyncio (>=3.4.3,<4.0.0)
Requires-Dist: dnspython (>=2.6.1,<3.0.0)
Requires-Dist: motor (>=3.3.2,<4.0.0)
Requires-Dist: msgpack (>=1.0.8,<2.0.0)
Requires-Dist: pydantic (>=2.6.4,<3.0.0)
Requires-Dist: pydantic-mongo (>=2.1.2,<3.0.0)
Requires-Dist: redis (>=5.0.3,<6.0.0)
